{"type": "Feature", "id": 12514649, "properties": {"woe:id": 12514649, "woe:parent_id": 1353353, "woe:name": "Dahra Airport", "woe:placetype": 14, "woe:placetype_name": "Airport", "woe:lang": "ENG", "iso:country": "LY", "meta:provider": ["geoplanet:7.3.1", "geoplanet:7.3.2", "geoplanet:7.4.0", "geoplanet:7.4.1", "geoplanet:7.5.1", "geoplanet:7.5.2", "geoplanet:7.6.0", "geoplanet:7.8.1", "geoplanet:7.9.0", "geoplanet:7.10.0", "geoplanet:8.0.0", "woeplanet:8.0.0"], "meta:indexed": "2020-08-20T20:26:59.109606", "meta:updated": "2020-08-22T02:03:02.094487", "woe:hierarchy": {"continent": 24865670, "country": 23424882, "town": 0, "planet": 1, "county": 0, "suburb": 0, "state": 2346143, "region": 0, "localadmin": 0}, "woe:timezone_id": 28350728, "woe:hash": "smhxxvtyd6t0", "woe:centroid": [17.926701, 29.474701], "geom:latitude": 29.474701, "geom:longitude": 17.926701, "geom:hash": "smhxxvtyd6t0", "woe:latitude": 29.474701, "geom:centroid": [17.926701, 29.474701], "woe:longitude": 17.926701, "woe:repo": "woeplanet-airport-ly"}, "geometry": {"coordinates": [17.926701, 29.474701], "type": "Point"}}