{"type": "Feature", "id": 12514671, "geometry": {"type": "Point", "coordinates": [14.6503, 27.2386]}, "properties": {"woe:id": 12514671, "woe:parent_id": 1353272, "woe:name": "Taminhint Airport", "woe:placetype": 14, "woe:placetype_name": "Airport", "woe:lang": "ENG", "iso:country": "LY", "meta:provider": ["geoplanet:7.3.1", "geoplanet:7.3.2", "geoplanet:7.4.0", "geoplanet:7.4.1", "geoplanet:7.5.1", "geoplanet:7.5.2", "geoplanet:7.6.0", "geoplanet:7.8.1", "geoplanet:7.9.0", "geoplanet:7.10.0", "geoplanet:8.0.0", "woeplanet:8.0.0"], "meta:indexed": "2020-08-20T20:26:59.129129", "meta:updated": "2020-10-14T11:05:12.637032", "woe:hierarchy": {"continent": 24865670, "country": 23424882, "town": 0, "planet": 1, "county": 0, "suburb": 0, "state": 2346126, "region": 0, "localadmin": 0}, "woe:timezone_id": 28350728, "woe:hash": "skf6vqsh2ep6", "woe:centroid": [14.6503, 27.2386], "geom:latitude": 27.2386, "geom:longitude": 14.6503, "geom:hash": "skf6vqsh2ep6", "woe:latitude": 27.2386, "geom:centroid": [14.6503, 27.2386], "woe:longitude": 14.6503, "woe:repo": "woeplanet-airport-ly", "geom:area": 0.0, "woe:scale": 19}}