{"type": "Feature", "id": 12514682, "geometry": {"type": "Point", "coordinates": [20.076099, 30.871099]}, "properties": {"woe:id": 12514682, "woe:parent_id": 1352552, "woe:name": "Zuetina Airport", "woe:placetype": 14, "woe:placetype_name": "Airport", "woe:lang": "ENG", "iso:country": "LY", "meta:provider": ["geoplanet:7.3.1", "geoplanet:7.3.2", "geoplanet:7.4.0", "geoplanet:7.4.1", "geoplanet:7.5.1", "geoplanet:7.5.2", "geoplanet:7.6.0", "geoplanet:7.8.1", "geoplanet:7.9.0", "geoplanet:7.10.0", "geoplanet:8.0.0", "woeplanet:8.0.0"], "meta:indexed": "2020-08-20T20:26:59.138134", "meta:updated": "2020-10-14T11:05:12.646486", "woe:hierarchy": {"continent": 24865670, "country": 23424882, "town": 0, "planet": 1, "county": 0, "suburb": 0, "state": 2346130, "region": 0, "localadmin": 0}, "woe:timezone_id": 28350728, "woe:hash": "smqr8gfvpjbq", "woe:centroid": [20.076099, 30.871099], "geom:latitude": 30.871099, "geom:longitude": 20.076099, "geom:hash": "smqr8gfvpjbq", "woe:latitude": 30.871099, "geom:centroid": [20.076099, 30.871099], "woe:longitude": 20.076099, "woe:repo": "woeplanet-airport-ly", "geom:area": 0.0, "woe:scale": 19}}